.DS_Store
httprequests/__init__.py
httprequests/drEsSign.py
httprequests/httpFunctions.py
httprequests/librarytester.py
httprequests/philipsHue.py
httprequests-0.3.dist-info/DESCRIPTION.rst
httprequests-0.3.dist-info/METADATA
httprequests-0.3.dist-info/RECORD
httprequests-0.3.dist-info/WHEEL
httprequests-0.3.dist-info/metadata.json
httprequests-0.3.dist-info/top_level.txt
