Metadata-Version: 1.0
Name: httprequests
Version: 0.3
Summary: Abstracts HTTP requests to be easier to use
Home-page: https://github.com/mateoguaman/httprequests
Author: Mateo Guaman Castro
Author-email: mateo.guaman1998@gmail.com
License: MIT
Platform: UNKNOWN
